{
  "oleg": {
    "balance": 43.7485,
    "pnl": -10.577,
    "bets_total": 83,
    "bets_won": 20,
    "bets_lost": 21,
    "bets_pending": 1,
    "last_bet": {
      "time": "18:06",
      "side": "Up",
      "amount": 8.0,
      "status": "pending"
    },
    "last_win": {
      "time": "17:51",
      "side": "Down",
      "amount": 16.3265
    },
    "updated_at": "2026-03-09T11:06:25Z"
  },
  "anna": {
    "balance": 19.92,
    "pnl": 0.0,
    "bets_total": 0,
    "bets_won": 0,
    "bets_lost": 0,
    "bets_pending": 0,
    "last_bet": null,
    "last_win": null,
    "updated_at": null
  }
}